gitown/__init__.py
gitown/gitown.py
gitown-0.1.1.dist-info/AUTHORS.rst
gitown-0.1.1.dist-info/LICENSE
gitown-0.1.1.dist-info/METADATA
gitown-0.1.1.dist-info/WHEEL
gitown-0.1.1.dist-info/entry_points.txt
gitown-0.1.1.dist-info/top_level.txt
gitown-0.1.1.dist-info/RECORD
