Metadata-Version: 2.1
Name: gitown
Version: 0.1.1
Summary: Keep your github CODEOWNERS file up to date.
Home-page: https://github.com/milin/gitown
Author: Milind Shakya
Author-email: sh.milind@gmail.com
License: MIT license
Keywords: gitown
Platform: UNKNOWN
Classifier: Development Status :: 2 - Pre-Alpha
Classifier: Intended Audience :: Developers
Classifier: License :: OSI Approved :: MIT License
Classifier: Natural Language :: English
Classifier: Programming Language :: Python :: 3.6
Classifier: Programming Language :: Python :: 3.7
Classifier: Programming Language :: Python :: 3.8
Requires-Python: >=3.5
Requires-Dist: pre-commit
Requires-Dist: invoke
Requires-Dist: simplejson
